{
  "No": "(480) 923-5455",
  "tel": "4809235455",
  "mail": "info@gottagoportabletoilets.com",
  "baseUrl": "https://gottagoportabletoilets.com/",
  "host": "gottagoportabletoilets.com",
  "name": "Gotta Go Portable Toilets",
  "address": "2390 E Camelback Rd Suite 130, Phoenix, AZ 85016, United States",
  "service": "Portable Toilet Rental",
  "location": "Arizona, AZ",
  "zipCode": "85016",
  "bannerImage": "https://ik.imagekit.io/z6skgnupx/gottagoportabletoilets_com/Portable_Toilet_Rental_Service_ContactInfo_bannerImage_wpgtH3YsY.jpg",
  "logoImage": "https://ik.imagekit.io/h7rza8886p/Gotta%20Go%20Portable%20Toilets.png?updatedAt=1748589613539"
}